ogh/__init__.py
ogh/_version.py
ogh/ogh.py
ogh/ogh_meta.py
ogh/ogh_xarray_landlab.py
ogh/tests/__init__.py
ogh/tests/test_ogh.py
tutorials/CreatePNNLnetcdfFile_MultipleFiles.py
tutorials/__init__.py
tutorials/_version.py
tutorials/ecohydrology_model_functions.py
tutorials/ogh.py
tutorials/ogh_meta.py
tutorials/ogh_old.py
tutorials/ogh_xarray_landlab.py
tutorials/plant_competition_ca_lb_pap.py
tutorials/soil_moisture_dynamics_lb_pap.py
tutorials/vegetation_dynamics_lb_pap.py
ogh-0.2.1.dist-info/LICENSE
ogh-0.2.1.dist-info/METADATA
ogh-0.2.1.dist-info/WHEEL
ogh-0.2.1.dist-info/top_level.txt
ogh-0.2.1.dist-info/RECORD
