Metadata-Version: 2.1
Name: ogh
Version: 0.2.1
Summary: Tools for observing the terrestrial and aquatic surfaces of Earth
Home-page: https://github.com/Freshwater-Initiative/Observatory
Author: Jimmy Phuong
Author-email: jphuong@uw.edu
Maintainer: Landung Setiawan
Maintainer-email: landungs@uw.edu
License: MIT
Keywords: Freshwater,Intiative,Tools
Platform: UNKNOWN
Classifier: Development Status :: 3 - Alpha
Classifier: Intended Audience :: Developers
Classifier: Topic :: Software Development :: Build Tools
Classifier: License :: OSI Approved :: MIT License
Classifier: Operating System :: OS Independent
Classifier: Programming Language :: Python :: 2.7
Classifier: Programming Language :: Python :: 3.6
Classifier: Topic :: Software Development :: Libraries :: Python Modules
Classifier: Topic :: Scientific/Engineering
Requires-Dist: pandas
Requires-Dist: dask
Requires-Dist: descartes
Requires-Dist: geopandas
Requires-Dist: beautifulsoup4
Requires-Dist: basemap
Requires-Dist: wget
Requires-Dist: seaborn
Requires-Dist: landlab
Requires-Dist: xarray
Requires-Dist: matplotlib
